README.txt
setup.py
src/bda/__init__.py
src/bda.bfg.tile.egg-info/PKG-INFO
src/bda.bfg.tile.egg-info/SOURCES.txt
src/bda.bfg.tile.egg-info/dependency_links.txt
src/bda.bfg.tile.egg-info/namespace_packages.txt
src/bda.bfg.tile.egg-info/not-zip-safe
src/bda.bfg.tile.egg-info/requires.txt
src/bda.bfg.tile.egg-info/top_level.txt
src/bda/bfg/__init__.py
src/bda/bfg/tile/__init__.py
src/bda/bfg/tile/_api.py
src/bda/bfg/tile/_api.txt
src/bda/bfg/tile/tests.py
src/bda/bfg/tile/testdata/main1.pt
src/bda/bfg/tile/testdata/main2.pt
src/bda/bfg/tile/testdata/main3.pt
src/bda/bfg/tile/testdata/tile1.pt
src/bda/bfg/tile/testdata/tile2.pt
src/bda/bfg/tile/testdata/tile2_1.pt
src/bda/bfg/tile/testdata/tile3.pt