Metadata-Version: 1.0
Name: bda.bfg.tile
Version: 1.0
Summary: Handle web application parts as tiles.
Home-page: https://svn.bluedynamics.net/svn/internal/bda.tile
Author: BlueDynamics Alliance
Author-email: dev@bluedynamics.com
License: GNU General Public Licence
Platform: UNKNOWN
Classifier: Development Status :: 3 - Alpha
Classifier: Environment :: Web Environment
Classifier: Operating System :: OS Independent
Classifier: Programming Language :: Python
Classifier: Topic :: Internet :: WWW/HTTP :: Dynamic Content
